vite/__init__.py
vite/cli.py
vite/vite.py
vite-1.5.1.dist-info/LICENSE
vite-1.5.1.dist-info/METADATA
vite-1.5.1.dist-info/WHEEL
vite-1.5.1.dist-info/entry_points.txt
vite-1.5.1.dist-info/top_level.txt
vite-1.5.1.dist-info/RECORD
