Metadata-Version: 2.1
Name: vite
Version: 1.5.1
Summary: A simple and minimal static site generator.
Home-page: https://github.com/icyphox/vite
Author: Anirudh
Author-email: icyph0x@pm.me
License: MIT
Platform: UNKNOWN
Requires-Dist: markdown2
Requires-Dist: Jinja2
Requires-Dist: huepy
Requires-Dist: pygments
